#include "unsupportedaudiofileexception.h"

///*public*/ class UnsupportedAudioFileException extends Exception {

    /*public*/ UnsupportedAudioFileException::UnsupportedAudioFileException(QString string) : Exception(string){
        // <editor-fold defaultstate="collapsed" desc="Compiled Code">
        /* 0: aload_0
         * 1: aload_1
         * 2: invokespecial java/lang/Exception."<init>":(Ljava/lang/String;)V
         * 5: return
         *  */
        // </editor-fold>
    }

    /*public*/ UnsupportedAudioFileException::UnsupportedAudioFileException() {
        // <editor-fold defaultstate="collapsed" desc="Compiled Code">
        /* 0: aload_0
         * 1: invokespecial java/lang/Exception."<init>":()V
         * 4: return
         *  */
        // </editor-fold>
    }

    /*public*/ UnsupportedAudioFileException::UnsupportedAudioFileException(QString string, Throwable* thrwbl) : Exception(string, thrwbl) {
        // <editor-fold defaultstate="collapsed" desc="Compiled Code">
        /* 0: aload_0
         * 1: aload_1
         * 2: aload_2
         * 3: invokespecial java/lang/Exception."<init>":(Ljava/lang/String;Ljava/lang/Throwable;)V
         * 6: return
         *  */
        // </editor-fold>
    }

    /*public*/ UnsupportedAudioFileException::UnsupportedAudioFileException(Throwable* thrwbl) {
        // <editor-fold defaultstate="collapsed" desc="Compiled Code">
        /* 0: aload_0
         * 1: aload_1
         * 2: invokespecial java/lang/Exception."<init>":(Ljava/lang/Throwable;)V
         * 5: return
         *  */
        // </editor-fold>
    }
//}
